grabio/__init__.py
grabio/extractor.py
grabio/user_agents.py
grabio/utils.py
grabio-1.2.dist-info/METADATA
grabio-1.2.dist-info/WHEEL
grabio-1.2.dist-info/top_level.txt
grabio-1.2.dist-info/RECORD
