Metadata-Version: 2.2
Name: grabio
Version: 1.2
Summary: Website information extractor library
Home-page: https://github.com/xr-xr4/grabio
Author: Ahmed Saoud
Author-email: ahmedsaoud0work@gmail.com
Classifier: Programming Language :: Python :: 3
Classifier: License :: OSI Approved :: MIT License
Classifier: Operating System :: OS Independent
Requires-Python: >=3.6
Requires-Dist: requests
Requires-Dist: beautifulsoup4
Requires-Dist: user_agent
Requires-Dist: python-whois
Dynamic: author
Dynamic: author-email
Dynamic: classifier
Dynamic: description
Dynamic: description-content-type
Dynamic: home-page
Dynamic: requires-dist
Dynamic: requires-python
Dynamic: summary
